scitiff/__init__.py
scitiff/_json_helpers.py
scitiff/_schema.py
scitiff/data.py
scitiff/executables.py
scitiff/io.py
scitiff/py.typed
scitiff/validator.py
scitiff/_resources/__init__.py
scitiff/_resources/metadata-schema.json
scitiff-25.7.0.dist-info/licenses/LICENSE
scitiff-25.7.0.dist-info/METADATA
scitiff-25.7.0.dist-info/WHEEL
scitiff-25.7.0.dist-info/entry_points.txt
scitiff-25.7.0.dist-info/top_level.txt
scitiff-25.7.0.dist-info/RECORD
