Metadata-Version: 2.4
Name: scitiff
Version: 25.7.0
Summary: Scientific tiff format for imaging experiments.
Author: Scipp contributors
License-Expression: BSD-3-Clause
Project-URL: Bug Tracker, https://github.com/scipp/scitiff/issues
Project-URL: Documentation, https://scipp.github.io/scitiff
Project-URL: Source, https://github.com/scipp/scitiff
Classifier: Intended Audience :: Science/Research
Classifier: Natural Language :: English
Classifier: Operating System :: OS Independent
Classifier: Programming Language :: Python :: 3
Classifier: Programming Language :: Python :: 3 :: Only
Classifier: Programming Language :: Python :: 3.10
Classifier: Programming Language :: Python :: 3.11
Classifier: Programming Language :: Python :: 3.12
Classifier: Topic :: Scientific/Engineering
Classifier: Typing :: Typed
Requires-Python: >=3.10
License-File: LICENSE
Requires-Dist: scipp
Requires-Dist: tifffile
Requires-Dist: jsonschema
Requires-Dist: pydantic
Provides-Extra: test
Requires-Dist: pytest; extra == "test"
Provides-Extra: gui
Requires-Dist: textual; extra == "gui"
Dynamic: license-file
